spideradmin/__init__.py
spideradmin/default_config.py
spideradmin/run.py
spideradmin/version.py
spideradmin/api_app/__init__.py
spideradmin/api_app/controller.py
spideradmin/api_app/scrapyd_utils.py
spideradmin/api_app/scrapyd_api/__init__.py
spideradmin/api_app/scrapyd_api/client.py
spideradmin/api_app/scrapyd_api/compat.py
spideradmin/api_app/scrapyd_api/constants.py
spideradmin/api_app/scrapyd_api/exceptions.py
spideradmin/api_app/scrapyd_api/wrapper.py
spideradmin/html_app/__init__.py
spideradmin/html_app/controller.py
spideradmin/scheduler_app/__init__.py
spideradmin/scheduler_app/controller.py
spideradmin/scheduler_app/scheduler_history.py
spideradmin/scheduler_app/utils.py
spideradmin/static/favicon.ico
spideradmin/static/favicon.jpeg
spideradmin/static/element-ui/axios.min.map
spideradmin/static/element-ui/axios@0.18.0.min.js
spideradmin/static/element-ui/element-ui@2.9.1.css
spideradmin/static/element-ui/element-ui@2.9.1.js
spideradmin/static/element-ui/vue@2.6.10.js
spideradmin/static/element-ui/fonts/element-icons.woff
spideradmin/static/js/echarts.min.js
spideradmin/static/js/jquery.cookie@1.4.1.min.js
spideradmin/static/js/jquery@3.4.1.min.js
spideradmin/templates/admin-vue.html
spideradmin/templates/item-line-vue.html
spideradmin/templates/item-vue.html
spideradmin/templates/job-vue.html
spideradmin/templates/line-vue.html
spideradmin/templates/project-vue.html
spideradmin/templates/scheduler-modify-vue.html
spideradmin/templates/scheduler-vue.html
spideradmin/templates/server-status-vue.html
spideradmin/templates/server-vue.html
spideradmin/templates/spider-vue.html
SpiderAdmin-0.0.32.dist-info/METADATA
SpiderAdmin-0.0.32.dist-info/WHEEL
SpiderAdmin-0.0.32.dist-info/entry_points.txt
SpiderAdmin-0.0.32.dist-info/top_level.txt
SpiderAdmin-0.0.32.dist-info/zip-safe
SpiderAdmin-0.0.32.dist-info/RECORD
