Metadata-Version: 2.1
Name: SpiderAdmin
Version: 0.0.32
Summary: a spider admin based scrapyd api and APScheduler
Home-page: https://github.com/mouday/SpiderAdmin
Author: Peng Shiyu
Author-email: pengshiyuyx@gmail.com
License: MIT
Keywords: spider admin
Platform: UNKNOWN
Classifier: Programming Language :: Python :: 3
Classifier: Programming Language :: Python :: 3.6
Requires-Dist: requests (>=2.22.0)
Requires-Dist: Flask (>=1.0.3)
Requires-Dist: APScheduler (>=3.6.0)
Requires-Dist: tinydb (>=3.13.0)
Requires-Dist: Flask-BasicAuth (>=0.2.0)
Requires-Dist: python-dateutil (>=2.6.0)
Requires-Dist: SQLAlchemy (>=1.3.3)
